slog/__init__.py
slog/slog.py
slog-0.5.5.dist-info/DESCRIPTION.rst
slog-0.5.5.dist-info/METADATA
slog-0.5.5.dist-info/RECORD
slog-0.5.5.dist-info/WHEEL
slog-0.5.5.dist-info/metadata.json
slog-0.5.5.dist-info/top_level.txt
