Metadata-Version: 2.0
Name: slog
Version: 0.5.5
Summary: A simple logging library
Home-page: https://github.com/verandaguy/slog
Author: Jules Mazur
Author-email: julesmazur [ at ] gmail [ dot ] com
License: MIT
Download-URL: https://raw.githubusercontent.com/verandaguy/slog/master/slog.py
Keywords: logging,log,simple
Platform: UNKNOWN
Classifier: Development Status :: 4 - Beta
Classifier: Environment :: Console
Classifier: Intended Audience :: Developers
Classifier: Natural Language :: English
Classifier: Operating System :: POSIX
Classifier: Programming Language :: Python :: 2
Classifier: Topic :: Software Development :: Bug Tracking
Classifier: Topic :: Software Development :: Quality Assurance
Classifier: Topic :: Software Development :: Testing
Classifier: Topic :: System :: Logging
Classifier: Topic :: Terminals
Classifier: Topic :: Utilities
Requires-Dist: termcolor
